svlearn_fathersday/__init__.py
pdf_downloads-0.1.0.dist-info/METADATA
pdf_downloads-0.1.0.dist-info/WHEEL
pdf_downloads-0.1.0.dist-info/RECORD
