Metadata-Version: 2.4
Name: pdf-downloads
Version: 0.1.0
Summary: A simple library to download pdf files from the web by scraping.
Requires-Python: >=3.12
Requires-Dist: svlearn-bootcamp>=0.1.7
